song/__init__.py
song/slit.py
song/song.py
song/thar.py
song/utils.py
song/calibration/README.md
song/calibration/thar.dat
song/calibration/thar_line_list.dump
song/calibration/thar_temp.dump
song/calibration/thar_template.fits
song/calibration/wave_temp.dump
songcn/__init__.py
songcn/config.py
songcn/imageio.py
songcn/main_script.py
songcn/observation.py
songcn/config/songcn_default.yml
songcn/config/songcn_params.yml
songcn/core/__init__.py
songcn/core/aperture.py
songcn/core/background.py
songcn/core/calibration.py
songcn/core/extraction.py
songcn/core/flux.py
songcn/core/polynomial.py
songcn/core/pv2002.py
songcn/core/visualization.py
songcn/core/wavelength.py
songcn/core/trace/__init__.py
songcn/core/trace/local_max.py
songcn/core/trace/trace_for_gui.py
twodspec/__init__.py
twodspec/aperture.py
twodspec/aprec.py
twodspec/background.py
twodspec/calibration.py
twodspec/ccd.py
twodspec/extract.py
twodspec/polynomial.py
twodspec/thar.py
twodspec/trace.py
twodspec/trace2.py
twodspec/deprecated/__init__.py
twodspec/deprecated/aperture_20170523.py
twodspec/deprecated/aperture_20200330.py
twodspec/deprecated/approfile.py
twodspec/deprecated/aprec.py
twodspec/deprecated/ccdproc_mod.py
twodspec/deprecated/master_.py
twodspec/deprecated/newtrace.py
twodspec/deprecated/normalization.py
twodspec/deprecated/pyreduce.py
twodspec/deprecated/stella.py
twodspec/extern/__init__.py
twodspec/extern/interpolate.py
twodspec/extern/polynomial.py
songcn-0.1.3.dist-info/LICENSE
songcn-0.1.3.dist-info/METADATA
songcn-0.1.3.dist-info/WHEEL
songcn-0.1.3.dist-info/top_level.txt
songcn-0.1.3.dist-info/RECORD
