Metadata-Version: 2.1
Name: songcn
Version: 0.1.3
Summary: The SONG-China data processing pipeline.
Home-page: http://github.com/hypergravity/songcn
Author: Bo Zhang
Author-email: bozhang@nao.cas.cn
License: MIT
Classifier: Development Status :: 5 - Production/Stable
Classifier: Intended Audience :: Science/Research
Classifier: License :: OSI Approved :: MIT License
Classifier: Operating System :: OS Independent
Classifier: Programming Language :: Python :: 3.7
Classifier: Topic :: Scientific/Engineering :: Physics
Classifier: Topic :: Scientific/Engineering :: Astronomy
License-File: LICENSE
